MANIFEST.in
README.md
meta.json
setup.py
es_tori_sep/__init__.py
es_tori_sep/meta.json
es_tori_sep.egg-info/PKG-INFO
es_tori_sep.egg-info/SOURCES.txt
es_tori_sep.egg-info/dependency_links.txt
es_tori_sep.egg-info/entry_points.txt
es_tori_sep.egg-info/not-zip-safe
es_tori_sep.egg-info/requires.txt
es_tori_sep.egg-info/top_level.txt
es_tori_sep/es_tori_sep-0.0.1/README.md
es_tori_sep/es_tori_sep-0.0.1/config.cfg
es_tori_sep/es_tori_sep-0.0.1/meta.json
es_tori_sep/es_tori_sep-0.0.1/tokenizer
es_tori_sep/es_tori_sep-0.0.1/ner/cfg
es_tori_sep/es_tori_sep-0.0.1/ner/model
es_tori_sep/es_tori_sep-0.0.1/ner/moves
es_tori_sep/es_tori_sep-0.0.1/tok2vec/cfg
es_tori_sep/es_tori_sep-0.0.1/tok2vec/model
es_tori_sep/es_tori_sep-0.0.1/vocab/key2row
es_tori_sep/es_tori_sep-0.0.1/vocab/lookups.bin
es_tori_sep/es_tori_sep-0.0.1/vocab/strings.json
es_tori_sep/es_tori_sep-0.0.1/vocab/vectors
es_tori_sep/es_tori_sep-0.0.1/vocab/vectors.cfg