Metadata-Version: 1.0
Name: es-tori-sep
Version: 0.0.1
Summary: This is a tori name entity recognizer using spacy splitting names into FORENAMES and SURNAMES
Home-page: UNKNOWN
Author: emptor
Author-email: UNKNOWN
License: MIT
Platform: UNKNOWN
